[
  {
    "id": "chanakya-friend",
    "text": "There is some self-interest behind every friendship. There is no friendship without self-interests. This is a bitter truth.",
    "author": "Chanakya",
    "source": "Attributed to Chanakya (Chanakya Niti), ancient India",
    "lesson": "See the incentives clearly, even inside relationships.",
    "category": "Practical Wisdom",
    "action": "Name one relationship where you give more than you take, then send that person a genuine message today.",
    "genre": "Eastern Wisdom",
    "sourceType": "Aphorism"
  },
  {
    "id": "osho-sky",
    "text": "Your being is vast like the sky; don't identify with the passing clouds.",
    "author": "Osho (Rajneesh)",
    "source": "Attributed to Osho (Rajneesh)",
    "lesson": "You are the awareness, not the passing moods.",
    "category": "Consciousness",
    "action": "Write down the mood you woke up in, then add 'this is a cloud, not me' under it.",
    "genre": "Eastern Wisdom",
    "sourceType": "Aphorism"
  },
  {
    "id": "vivekananda-arise",
    "text": "Arise, awake, and stop not till the goal is reached.",
    "author": "Swami Vivekananda",
    "source": "Swami Vivekananda's rallying call (from the Katha Upanishad)",
    "lesson": "Commit fully and persist until it's done.",
    "category": "Resolve",
    "action": "Pick the one goal you keep half-finishing and block 30 minutes for it on your calendar now.",
    "genre": "Eastern Wisdom",
    "sourceType": "Scripture"
  },
  {
    "id": "meadows-dance",
    "text": "We can't control systems or figure them out. But we can dance with them.",
    "author": "Donella Meadows",
    "source": "'Dancing with Systems' (Whole Earth Review, 2001); Thinking in Systems, ch. 7",
    "lesson": "Work with a system's feedback instead of trying to dominate it.",
    "category": "Systems Thinking",
    "action": "Name one metric you keep forcing, then write the next small nudge instead of the big fix.",
    "genre": "Systems & Science",
    "sourceType": "Book"
  },
  {
    "id": "bateson-difference",
    "text": "Information is a difference that makes a difference.",
    "author": "Gregory Bateson",
    "source": "Steps to an Ecology of Mind (1972), 'Form, Substance and Difference'",
    "lesson": "Meaning comes from contrast and context, not raw data.",
    "category": "Systems Thinking",
    "action": "Open your dashboard and circle the one number that changed; ignore the rest for now.",
    "genre": "Systems & Science",
    "sourceType": "Book"
  },
  {
    "id": "boulding-growth",
    "text": "Anyone who believes exponential growth can go on forever in a finite world is either a madman or an economist.",
    "author": "Kenneth Boulding",
    "source": "Attributed; popularized via Mancur Olson, Daedalus (1973); exact origin disputed",
    "lesson": "Nothing compounds forever in a bounded system.",
    "category": "Systems Thinking",
    "action": "Write down one growth number you assume is forever, then add the limit that will eventually stop it.",
    "genre": "Systems & Science",
    "sourceType": "Aphorism"
  },
  {
    "id": "daly-liquidation",
    "text": "There is something fundamentally wrong in treating the Earth as if it were a business in liquidation.",
    "author": "Herman E. Daly",
    "source": "Steady-State Economics, 2nd ed. (1991), p. 248",
    "lesson": "Don't burn your capital base for short-term flow.",
    "category": "Systems Thinking",
    "action": "Name one long-term asset you're burning for this week's numbers, then text a teammate about protecting it.",
    "genre": "Systems & Science",
    "sourceType": "Book"
  },
  {
    "id": "einstein-curiosity",
    "text": "The important thing is not to stop questioning. Curiosity has its own reason for existing.",
    "author": "Albert Einstein",
    "source": "Quoted by William Miller, LIFE magazine, 2 May 1955",
    "lesson": "Protect your 'holy curiosity'; never stop asking why.",
    "category": "Curiosity",
    "action": "Write one 'why does this work this way' question about your product and send it to someone who'd know.",
    "genre": "Systems & Science",
    "sourceType": "Interview"
  },
  {
    "id": "hardin-commons",
    "text": "Freedom in a commons brings ruin to all.",
    "author": "Garrett Hardin",
    "source": "'The Tragedy of the Commons,' Science (1968)",
    "lesson": "Shared resources need shared rules.",
    "category": "Systems Thinking",
    "action": "Pick one shared resource your team overuses and propose one simple rule for it in your group chat.",
    "genre": "Systems & Science",
    "sourceType": "Book"
  },
  {
    "id": "havel-hope",
    "text": "Hope is not the conviction that something will turn out well, but the certainty that something makes sense, regardless of how it turns out.",
    "author": "Vaclav Havel",
    "source": "Disturbing the Peace (1990), pp. 181-182",
    "lesson": "Hope is about meaning, not optimism about outcomes.",
    "category": "Hope",
    "action": "Write one sentence on why your current project matters even if it fails, and pin it to your desk.",
    "genre": "Mind & Character",
    "sourceType": "Book"
  },
  {
    "id": "mumford-clock",
    "text": "The clock, not the steam-engine, is the key-machine of the modern industrial age.",
    "author": "Lewis Mumford",
    "source": "Technics and Civilization (1934)",
    "lesson": "The tools we adopt quietly reshape how we live.",
    "category": "Technology & Society",
    "action": "Name one tool you use daily, then write down one habit it quietly forced on you.",
    "genre": "Systems & Science",
    "sourceType": "Book"
  },
  {
    "id": "myrdal-softstate",
    "text": "A 'soft state' is undone not by bad laws but by laws no one enforces.",
    "author": "Gunnar Myrdal",
    "source": "Paraphrase of Myrdal's thesis in Asian Drama (1968) - concept, not a verbatim quote",
    "lesson": "Rules without enforcement are theater.",
    "category": "Development",
    "action": "Pick one team rule everyone ignores; either enforce it today or delete it from your docs.",
    "genre": "Systems & Science",
    "sourceType": "Book"
  },
  {
    "id": "schumacher-small",
    "text": "Small is beautiful.",
    "author": "E. F. Schumacher",
    "source": "Small Is Beautiful: Economics as if People Mattered (1973); phrase from Leopold Kohr",
    "lesson": "Human-scale often beats relentless bigness.",
    "category": "Economics",
    "action": "Find one bloated process or feature and write down the smaller version you could ship instead.",
    "genre": "Systems & Science",
    "sourceType": "Book"
  },
  {
    "id": "marcus-mind",
    "text": "You have power over your mind, not outside events. Realize this, and you will find strength.",
    "author": "Marcus Aurelius",
    "source": "Meditations (popular translation)",
    "lesson": "Control the controllable: your own response.",
    "category": "Stoicism",
    "action": "List one thing stressing you, then cross out everything on it you cannot actually control.",
    "genre": "Stoicism",
    "sourceType": "Book"
  },
  {
    "id": "seneca-imagination",
    "text": "We suffer more often in imagination than in reality.",
    "author": "Seneca",
    "source": "Letters from a Stoic (Letters to Lucilius)",
    "lesson": "Don't pre-pay suffering for things that never happen.",
    "category": "Stoicism",
    "action": "Write down the worst-case scenario you're dreading, then rate how likely it really is, one to ten.",
    "genre": "Stoicism",
    "sourceType": "Letter"
  },
  {
    "id": "laotzu-journey",
    "text": "The journey of a thousand miles begins with a single step.",
    "author": "Lao Tzu",
    "source": "Tao Te Ching, ch. 64",
    "lesson": "Start. Momentum compounds.",
    "category": "Action",
    "action": "Pick the project you keep postponing and do the smallest first step in the next five minutes.",
    "genre": "Eastern Wisdom",
    "sourceType": "Scripture"
  },
  {
    "id": "socrates-examined",
    "text": "The unexamined life is not worth living.",
    "author": "Socrates",
    "source": "Plato's Apology (38a)",
    "lesson": "Reflection is what makes a life your own.",
    "category": "Philosophy",
    "action": "Write down one decision you made today and the real reason behind it, not the stated one.",
    "genre": "Mind & Character",
    "sourceType": "Book"
  },
  {
    "id": "durant-excellence",
    "text": "We are what we repeatedly do. Excellence, then, is not an act, but a habit.",
    "author": "Will Durant",
    "source": "The Story of Philosophy (1926), summarizing Aristotle (commonly misattributed to Aristotle)",
    "lesson": "Excellence is a routine, not a one-off moment.",
    "category": "Habits",
    "action": "Name the one daily action that defines your craft, then do it once right now.",
    "genre": "Craft & Creativity",
    "sourceType": "Book"
  },
  {
    "id": "roosevelt-arena",
    "text": "The credit belongs to the man who is actually in the arena, whose face is marred by dust and sweat and blood.",
    "author": "Theodore Roosevelt",
    "source": "'Citizenship in a Republic,' Paris (1910)",
    "lesson": "Doers, not critics, earn the credit.",
    "category": "Courage",
    "action": "Pick one thing you've only been critiquing from the sidelines and take one real step on it today.",
    "genre": "Mind & Character",
    "sourceType": "Book"
  },
  {
    "id": "mandela-impossible",
    "text": "It always seems impossible until it's done.",
    "author": "Nelson Mandela",
    "source": "Widely attributed to Nelson Mandela",
    "lesson": "Big goals look unreachable until reached.",
    "category": "Perseverance",
    "action": "Write down the goal that feels impossible, then list the one move you'd make if it weren't.",
    "genre": "Mind & Character",
    "sourceType": "Aphorism"
  },
  {
    "id": "angelou-feel",
    "text": "People will never forget how you made them feel.",
    "author": "Maya Angelou",
    "source": "Maya Angelou (widely attributed)",
    "lesson": "Emotional impact outlasts words and deeds.",
    "category": "Leadership",
    "action": "Text one person who helped you recently and tell them exactly how they made you feel.",
    "genre": "Craft & Creativity",
    "sourceType": "Aphorism"
  },
  {
    "id": "frankl-change",
    "text": "When we are no longer able to change a situation, we are challenged to change ourselves.",
    "author": "Viktor Frankl",
    "source": "Man's Search for Meaning (1946)",
    "lesson": "Change your response when you can't change the world.",
    "category": "Resilience",
    "action": "Name one stuck situation you can't fix, then write down one thing about your own response you can change.",
    "genre": "Mind & Character",
    "sourceType": "Book"
  },
  {
    "id": "nietzsche-why",
    "text": "He who has a why to live for can bear almost any how.",
    "author": "Friedrich Nietzsche",
    "source": "Twilight of the Idols (1888)",
    "lesson": "A strong purpose makes hard means bearable.",
    "category": "Purpose",
    "action": "Write the one-line reason you're building this, and keep it where you'll see it when it gets hard.",
    "genre": "Mind & Character",
    "sourceType": "Book"
  },
  {
    "id": "mlk-right",
    "text": "The time is always right to do what is right.",
    "author": "Martin Luther King Jr.",
    "source": "Oberlin College address (1965)",
    "lesson": "Don't wait for a convenient moment to act rightly.",
    "category": "Ethics",
    "action": "Pick one right thing you've been delaying for a better moment and do the first part of it now.",
    "genre": "Mind & Character",
    "sourceType": "Speech"
  },
  {
    "id": "curie-understood",
    "text": "Nothing in life is to be feared, it is only to be understood.",
    "author": "Marie Curie",
    "source": "Marie Curie (widely attributed)",
    "lesson": "Understanding dissolves fear.",
    "category": "Courage",
    "action": "Name one thing at work that scares you, then write down one fact that makes it less unknown.",
    "genre": "Systems & Science",
    "sourceType": "Aphorism"
  },
  {
    "id": "jung-unconscious",
    "text": "Until you make the unconscious conscious, it will direct your life and you will call it fate.",
    "author": "Carl Jung",
    "source": "Attributed to Carl Jung (exact source debated)",
    "lesson": "Examine your patterns or be ruled by them.",
    "category": "Psychology",
    "action": "Write down one pattern you keep repeating in your work, then name its real trigger.",
    "genre": "Mind & Character",
    "sourceType": "Aphorism"
  },
  {
    "id": "thoreau-dreams",
    "text": "If one advances confidently in the direction of his dreams, he will meet with a success unexpected in common hours.",
    "author": "Henry David Thoreau",
    "source": "Walden (1854)",
    "lesson": "Move toward what you want; ordinary limits bend.",
    "category": "Action",
    "action": "Write one bold thing you actually want, then take one visible step toward it today.",
    "genre": "Craft & Creativity",
    "sourceType": "Book"
  },
  {
    "id": "sagan-starstuff",
    "text": "We are made of star-stuff.",
    "author": "Carl Sagan",
    "source": "Cosmos (1980)",
    "lesson": "Zoom out: you're part of something vast.",
    "category": "Wonder",
    "action": "Step away from the screen for sixty seconds and name one thing bigger than today's deadline.",
    "genre": "Systems & Science",
    "sourceType": "Book"
  },
  {
    "id": "gandhi-forgive",
    "text": "The weak can never forgive. Forgiveness is the attribute of the strong.",
    "author": "Mahatma Gandhi",
    "source": "Attributed to Mahatma Gandhi",
    "lesson": "Forgiveness is strength, not surrender.",
    "category": "Character",
    "action": "Think of one person you're holding a grudge against and write down one thing you'll let go of.",
    "genre": "Eastern Wisdom",
    "sourceType": "Aphorism"
  },
  {
    "id": "jobs-time",
    "text": "Your time is limited, so don't waste it living someone else's life.",
    "author": "Steve Jobs",
    "source": "Stanford commencement (2005)",
    "lesson": "Live by conviction, not others' expectations.",
    "category": "Focus",
    "action": "Name one thing on your list you're doing only to meet someone else's expectation, then question it.",
    "genre": "Building & Startups",
    "sourceType": "Speech"
  },
  {
    "id": "buffett-value",
    "text": "Price is what you pay. Value is what you get.",
    "author": "Warren Buffett",
    "source": "Berkshire Hathaway shareholder letter (2008)",
    "lesson": "Worth and price are not the same thing.",
    "category": "Money",
    "action": "Pick one recent purchase or hire and write down what you paid versus what you actually got.",
    "genre": "Strategy & Money",
    "sourceType": "Letter"
  },
  {
    "id": "munger-compound",
    "text": "The first rule of compounding: never interrupt it unnecessarily.",
    "author": "Charlie Munger",
    "source": "Attributed to Charlie Munger",
    "lesson": "Let good things compound; stop tinkering.",
    "category": "Patience",
    "action": "Name one good thing you keep tinkering with, then commit to leaving it untouched this week.",
    "genre": "Strategy & Money",
    "sourceType": "Aphorism"
  },
  {
    "id": "gates-success",
    "text": "Success is a lousy teacher. It seduces smart people into thinking they can't lose.",
    "author": "Bill Gates",
    "source": "The Road Ahead (1995)",
    "lesson": "Winning breeds complacency; stay alert.",
    "category": "Mindset",
    "action": "Write down one recent win, then list one thing it's making you lazy or overconfident about.",
    "genre": "Building & Startups",
    "sourceType": "Book"
  },
  {
    "id": "musk-odds",
    "text": "When something is important enough, you do it even if the odds are not in your favor.",
    "author": "Elon Musk",
    "source": "60 Minutes interview (2012)",
    "lesson": "Let importance, not odds, drive big bets.",
    "category": "Courage",
    "action": "Name one important bet you're avoiding because the odds look bad, then write its first step.",
    "genre": "Building & Startups",
    "sourceType": "Interview"
  },
  {
    "id": "naval-wealth",
    "text": "Seek wealth, not money or status.",
    "author": "Naval Ravikant",
    "source": "'How to Get Rich' thread (2018)",
    "lesson": "Build assets that earn while you sleep.",
    "category": "Wealth",
    "action": "Write down one asset you could build that earns without your time, then sketch its first piece.",
    "genre": "Building & Startups",
    "sourceType": "Book"
  },
  {
    "id": "graham-want",
    "text": "Make something people want.",
    "author": "Paul Graham",
    "source": "Y Combinator motto, from Paul Graham's essays",
    "lesson": "Nothing else matters if the thing isn't wanted.",
    "category": "Building",
    "action": "Message one user today and ask the one question: would you be upset if this disappeared?",
    "genre": "Building & Startups",
    "sourceType": "Essay"
  },
  {
    "id": "thiel-competition",
    "text": "Competition is for losers.",
    "author": "Peter Thiel",
    "source": "Peter Thiel, WSJ essay (2014), from Zero to One",
    "lesson": "Differentiate until you're irreplaceable.",
    "category": "Strategy",
    "action": "Write down the one thing your product does that no rival can copy easily, and sharpen it in a sentence.",
    "genre": "Strategy & Money",
    "sourceType": "Essay"
  },
  {
    "id": "hoffman-launch",
    "text": "If you're not embarrassed by the first version of your product, you've launched too late.",
    "author": "Reid Hoffman",
    "source": "Reid Hoffman (widely cited and confirmed by him)",
    "lesson": "Ship early; real feedback beats polish.",
    "category": "Shipping",
    "action": "Find one feature you're over-polishing and set a timer to ship the rough version today.",
    "genre": "Building & Startups",
    "sourceType": "Aphorism"
  },
  {
    "id": "horowitz-bullets",
    "text": "There are no silver bullets, only lead bullets.",
    "author": "Ben Horowitz",
    "source": "The Hard Thing About Hard Things (2014)",
    "lesson": "Hard problems need direct work, not shortcuts.",
    "category": "Execution",
    "action": "Name the hard problem you keep avoiding and write down the direct, unglamorous work it actually needs.",
    "genre": "Building & Startups",
    "sourceType": "Book"
  },
  {
    "id": "nadella-innov",
    "text": "Our industry does not respect tradition. It only respects innovation.",
    "author": "Satya Nadella",
    "source": "On becoming Microsoft CEO (2014)",
    "lesson": "Reinvent before you're forced to.",
    "category": "Change",
    "action": "Name one thing you do 'because we've always done it' and write down what would replace it.",
    "genre": "Building & Startups",
    "sourceType": "Book"
  },
  {
    "id": "zuck-risk",
    "text": "The biggest risk is not taking any risk.",
    "author": "Mark Zuckerberg",
    "source": "Y Combinator Startup School (2011)",
    "lesson": "In fast change, standing still is riskiest.",
    "category": "Risk",
    "action": "Write down one safe choice you're defaulting to, then name the risk you're avoiding by it.",
    "genre": "Building & Startups",
    "sourceType": "Book"
  },
  {
    "id": "cuban-work",
    "text": "Work like there is someone working 24 hours a day to take it all away from you.",
    "author": "Mark Cuban",
    "source": "How to Win at the Sport of Business (2011)",
    "lesson": "Treat your edge as always under threat.",
    "category": "Hustle",
    "action": "Name one competitor who could take your edge, then write the one move you'd make to defend it today.",
    "genre": "Building & Startups",
    "sourceType": "Book"
  },
  {
    "id": "dalio-progress",
    "text": "Pain plus reflection equals progress.",
    "author": "Ray Dalio",
    "source": "Principles (2017)",
    "lesson": "Reflect on pain to convert it into growth.",
    "category": "Growth",
    "action": "Write down one recent painful mistake and the single lesson you'll carry forward from it.",
    "genre": "Strategy & Money",
    "sourceType": "Book"
  },
  {
    "id": "clear-systems",
    "text": "You do not rise to the level of your goals. You fall to the level of your systems.",
    "author": "James Clear",
    "source": "Atomic Habits (2018)",
    "lesson": "Design the process, not just the target.",
    "category": "Habits",
    "action": "Pick one goal you keep missing and design one small system or trigger that makes it automatic.",
    "genre": "Mind & Character",
    "sourceType": "Book"
  },
  {
    "id": "sinek-why",
    "text": "People don't buy what you do; they buy why you do it.",
    "author": "Simon Sinek",
    "source": "Start With Why (2009) / TED talk",
    "lesson": "Purpose creates loyalty.",
    "category": "Purpose",
    "action": "Write your product's 'why' in one sentence a customer would actually repeat to a friend.",
    "genre": "Building & Startups",
    "sourceType": "Book"
  },
  {
    "id": "ferriss-uncomf",
    "text": "A person's success in life can usually be measured by the number of uncomfortable conversations they're willing to have.",
    "author": "Tim Ferriss",
    "source": "The 4-Hour Workweek (2007)",
    "lesson": "Growth hides behind the conversation you're avoiding.",
    "category": "Courage",
    "action": "Name the one conversation you're avoiding, then send the first message to schedule it today.",
    "genre": "Building & Startups",
    "sourceType": "Book"
  },
  {
    "id": "branson-train",
    "text": "Train people well enough so they can leave, treat them well enough so they don't want to.",
    "author": "Richard Branson",
    "source": "Richard Branson, posted on X (2014)",
    "lesson": "Invest in people; retention follows.",
    "category": "Leadership",
    "action": "Pick one person on your team and do one concrete thing today to make them better at their craft.",
    "genre": "Building & Startups",
    "sourceType": "Book"
  },
  {
    "id": "huang-character",
    "text": "Greatness comes from character, and character is formed out of people who suffered.",
    "author": "Jensen Huang",
    "source": "Jensen Huang, Stanford talk (2024)",
    "lesson": "Hardship builds the character behind greatness.",
    "category": "Resilience",
    "action": "Write down one hard thing you survived and the strength it gave you that you use now.",
    "genre": "Building & Startups",
    "sourceType": "Book"
  },
  {
    "id": "godin-stories",
    "text": "Marketing is no longer about the stuff you make, but the stories you tell.",
    "author": "Seth Godin",
    "source": "Seth Godin (theme of All Marketers Are Liars)",
    "lesson": "A believed story beats a feature list.",
    "category": "Marketing",
    "action": "Write the one-sentence story behind what you build, not the feature list, and test it on someone.",
    "genre": "Craft & Creativity",
    "sourceType": "Book"
  },
  {
    "id": "altman-love",
    "text": "It's better to have a small number of users that love you than a large number that like you.",
    "author": "Sam Altman",
    "source": "Sam Altman, Startup Playbook (Y Combinator)",
    "lesson": "Depth of love beats breadth of mild interest.",
    "category": "Building",
    "action": "Name your three most engaged users and message one of them to ask what they love most.",
    "genre": "Building & Startups",
    "sourceType": "Book"
  },
  {
    "id": "hormozi-hard",
    "text": "Everything worth doing is hard. The greater the payoff, the greater the hardship.",
    "author": "Alex Hormozi",
    "source": "Alex Hormozi, posted on X / $100M series",
    "lesson": "Difficulty filters out the competition.",
    "category": "Discipline",
    "action": "Pick the hardest task on your list and start it now, before the easy ones tempt you.",
    "genre": "Building & Startups",
    "sourceType": "Aphorism"
  },
  {
    "id": "andreessen-soft",
    "text": "Software is eating the world.",
    "author": "Marc Andreessen",
    "source": "Marc Andreessen, WSJ essay (2011)",
    "lesson": "Build on software or be absorbed by it.",
    "category": "Tech",
    "action": "Name one manual part of your work and write down how software could absorb it.",
    "genre": "Building & Startups",
    "sourceType": "Essay"
  },
  {
    "id": "bezos-brand",
    "text": "Your brand is what other people say about you when you're not in the room.",
    "author": "Jeff Bezos",
    "source": "Attributed to Jeff Bezos",
    "lesson": "Reputation forms in your absence.",
    "category": "Branding",
    "action": "Write down what you'd want people saying about you when you're not there, then act on one gap.",
    "genre": "Building & Startups",
    "sourceType": "Aphorism"
  },
  {
    "id": "karpathy-english",
    "text": "The hottest new programming language is English.",
    "author": "Andrej Karpathy",
    "source": "Andrej Karpathy, posted on X (January 2023)",
    "lesson": "Clear language is now real leverage.",
    "category": "AI",
    "action": "Take one fuzzy request you wrote today and rewrite it in plain, precise English.",
    "genre": "Building & Startups",
    "sourceType": "Aphorism"
  },
  {
    "id": "bezos-dayone",
    "text": "Day 2 is stasis. Followed by irrelevance. Followed by excruciating, painful decline. Followed by death. And that is why it is always Day 1.",
    "author": "Jeff Bezos",
    "source": "Amazon 2016 Letter to Shareholders",
    "lesson": "Treat every day as the start, not the coast.",
    "category": "complacency",
    "action": "Name one process your team runs on autopilot and write down how you'd build it fresh today.",
    "genre": "Building & Startups",
    "sourceType": "Letter"
  },
  {
    "id": "grove-paranoid",
    "text": "Success breeds complacency. Complacency breeds failure. Only the paranoid survive.",
    "author": "Andy Grove",
    "source": "Only the Paranoid Survive, Andrew S. Grove, 1996",
    "lesson": "A recent win is the moment to look hardest for the threat.",
    "category": "vigilance",
    "action": "List your last clear win, then write the one weakness it's tempting you to ignore right now.",
    "genre": "Building & Startups",
    "sourceType": "Book"
  },
  {
    "id": "graham-unscalable",
    "text": "The most common unscalable thing founders have to do at the start is to recruit users manually.",
    "author": "Paul Graham",
    "source": "Essay 'Do Things That Don't Scale,' Paul Graham, July 2013",
    "lesson": "Early on, hand-recruit users one by one; scale comes later.",
    "category": "traction",
    "action": "Pick five ideal users and send each a personal message inviting them to try your product today.",
    "genre": "Building & Startups",
    "sourceType": "Essay"
  },
  {
    "id": "andreessen-pmf",
    "text": "The only thing that matters is getting to product/market fit. Product/market fit means being in a good market with a product that can satisfy that market.",
    "author": "Marc Andreessen",
    "source": "Essay 'The Pmarca Guide to Startups, part 4: The only thing that matters,' Marc Andreessen, June 25, 2007",
    "lesson": "Until the market pulls your product, nothing else you do counts.",
    "category": "focus",
    "action": "Write one sentence describing the market you serve and how your product satisfies it right now.",
    "genre": "Building & Startups",
    "sourceType": "Essay"
  },
  {
    "id": "altman-hard",
    "text": "It's often easier to succeed with a hard startup than an easy one.",
    "author": "Sam Altman",
    "source": "Essay 'Hard Startups,' Sam Altman, 2019 (blog.samaltman.com)",
    "lesson": "An ambitious problem attracts the talent and belief an easy one can't.",
    "category": "ambition",
    "action": "Take your current idea and write down a harder, more ambitious version of the same thing.",
    "genre": "Building & Startups",
    "sourceType": "Essay"
  },
  {
    "id": "naval-longterm",
    "text": "Play long-term games with long-term people. All the returns in life, whether in wealth, relationships, or knowledge, come from compound interest.",
    "author": "Naval Ravikant",
    "source": "Naval Ravikant, X/Twitter, 23 March 2019 (tweet 1109704032204009473); collected in The Almanack of Naval Ravikant, 2020",
    "lesson": "Returns come from repeated games with the same trusted people.",
    "category": "compounding",
    "action": "Name one person you want a ten-year relationship with and do one small thing for them today.",
    "genre": "Building & Startups",
    "sourceType": "Aphorism"
  },
  {
    "id": "munger-invert",
    "text": "Invert, always invert.",
    "author": "Charlie Munger",
    "source": "Munger popularizing Carl Jacobi's maxim; collected in Poor Charlie's Almanack, 2005",
    "lesson": "Solve hard problems by figuring out how to fail and avoiding that.",
    "category": "thinking",
    "action": "Take the goal you're stuck on and write down every way it could fail, then dodge the top one.",
    "genre": "Strategy & Money",
    "sourceType": "Book"
  },
  {
    "id": "drucker-useless",
    "text": "There is surely nothing quite so useless as doing with great efficiency what should not be done at all.",
    "author": "Peter Drucker",
    "source": "Article 'Managing for Business Effectiveness,' Harvard Business Review, Peter Drucker, May 1963",
    "lesson": "Killing the wrong task beats doing it faster.",
    "category": "prioritization",
    "action": "Scan your to-do list and delete one task that shouldn't exist no matter how well it's done.",
    "genre": "Strategy & Money",
    "sourceType": "Essay"
  },
  {
    "id": "jobs-shipart",
    "text": "Real artists ship.",
    "author": "Steve Jobs",
    "source": "Steve Jobs to the Macintosh team, 1983 (documented by Andy Hertzfeld, folklore.org)",
    "lesson": "Finishing and releasing is part of the craft, not separate from it.",
    "category": "shipping",
    "action": "Pick one thing sitting nearly done in your drafts and put it in front of a real person today.",
    "genre": "Building & Startups",
    "sourceType": "Aphorism"
  },
  {
    "id": "carnegie-onebasket",
    "text": "Put all your eggs in one basket, and then watch that basket.",
    "author": "Andrew Carnegie",
    "source": "Andrew Carnegie, address 'The Road to Business Success,' Curry Commercial College, Pittsburgh, 23 June 1885 (pub. The Empire of Business, 1902)",
    "lesson": "Concentrate your bets, then guard them with full attention.",
    "category": "focus",
    "action": "Name the one bet that matters most this quarter and cut one side project that splits your focus.",
    "genre": "Building & Startups",
    "sourceType": "Speech"
  },
  {
    "id": "buffett-reputation",
    "text": "Lose money for the firm, and I will be understanding. Lose a shred of reputation for the firm, and I will be ruthless.",
    "author": "Warren Buffett",
    "source": "Warren Buffett, U.S. Congressional testimony on Salomon Brothers, September 1991",
    "lesson": "Money losses heal; a broken reputation rarely does.",
    "category": "reputation",
    "action": "Find one shortcut you're about to take that could dent trust, and choose the honest version instead.",
    "genre": "Strategy & Money",
    "sourceType": "Speech"
  },
  {
    "id": "marcus-obstacle",
    "text": "The impediment to action advances action. What stands in the way becomes the way.",
    "author": "Marcus Aurelius",
    "source": "Meditations, Book 5.20 (Gregory Hays translation, Modern Library, 2002)",
    "lesson": "The obstacle in front of you is the path, not a detour from it.",
    "category": "obstacles",
    "action": "Name the thing blocking your project and write down how working through it could become the win.",
    "genre": "Stoicism",
    "sourceType": "Book"
  },
  {
    "id": "marcus-dawn",
    "text": "At dawn, when you have trouble getting out of bed, tell yourself: \"I have to go to work — as a human being. What do I have to complain of, if I'm going to do what I was born for?\"",
    "author": "Marcus Aurelius",
    "source": "Meditations, Book 5.1 (Gregory Hays translation, Modern Library, 2002)",
    "lesson": "You were made to do the work; stop bargaining with the morning.",
    "category": "discipline",
    "action": "Pick the first real task of your day and start it before you check any messages or feeds.",
    "genre": "Stoicism",
    "sourceType": "Book"
  },
  {
    "id": "seneca-port",
    "text": "If a man does not know to what port he is steering, no wind is favorable to him.",
    "author": "Seneca",
    "source": "Letters from a Stoic (Epistulae Morales), Letter 71 (Richard Mott Gummere translation, Loeb Classical Library)",
    "lesson": "Without a clear destination, no effort points anywhere useful.",
    "category": "focus",
    "action": "Write the one specific outcome this week is steering toward, then check today's tasks against it.",
    "genre": "Stoicism",
    "sourceType": "Letter"
  },
  {
    "id": "epictetus-control",
    "text": "Some things are within our power, while others are not. Within our power are opinion, motivation, desire, aversion, and, in a word, whatever is of our own doing; not within our power are our body, our property, reputation, office, and, in a word, whatever is not of our own doing.",
    "author": "Epictetus",
    "source": "The Handbook (Enchiridion), ch. 1 (Robin Hard translation, Oxford World's Classics, 2014)",
    "lesson": "Spend energy on your choices, not on outcomes you can't command.",
    "category": "control",
    "action": "List what's worrying you, then split it into what you control and what you don't, and act on the first.",
    "genre": "Stoicism",
    "sourceType": "Book"
  },
  {
    "id": "laotzu-pine",
    "text": "The giant pine tree grows from a tiny sprout. The journey of a thousand miles starts from beneath your feet.",
    "author": "Lao Tzu",
    "source": "Tao Te Ching, ch. 64 (Stephen Mitchell translation, Harper & Row, 1988)",
    "lesson": "Big things grow from tiny, unglamorous starts.",
    "category": "beginnings",
    "action": "Pick the daunting project you keep postponing and plant the first small piece in the next five minutes.",
    "genre": "Eastern Wisdom",
    "sourceType": "Scripture"
  },
  {
    "id": "confucius-mound",
    "text": "It is like making a mound. If, when only one more basketful of earth is needed, I stop, then I have stopped. It is like leveling ground. Even if only one basketful is laid down, if I go on, then I am making progress.",
    "author": "Confucius",
    "source": "The Analects, Book 9.18 (Arthur Waley translation, 1938; numbered 9.19 in some editions)",
    "lesson": "Whether you finish or quit is your own choice, basket by basket.",
    "category": "persistence",
    "action": "Find the project that's one push from done and add that final basketful of work right now.",
    "genre": "Eastern Wisdom",
    "sourceType": "Scripture"
  },
  {
    "id": "confucius-knowing",
    "text": "The Master said, \"When you know a thing, to hold that you know it; and when you do not know a thing, to allow that you do not know it — this is knowledge.\"",
    "author": "Confucius",
    "source": "The Analects, Book 2.17 (James Legge translation, 1861)",
    "lesson": "Real knowledge is knowing the edge of what you know.",
    "category": "honesty",
    "action": "Write down one thing you've been pretending to understand, then admit it to the right person today.",
    "genre": "Eastern Wisdom",
    "sourceType": "Scripture"
  },
  {
    "id": "krishna-fruits",
    "text": "You have a right to your actions, but never to your actions' fruits. Act for the action's sake. And do not be attached to inaction.",
    "author": "Krishna (Bhagavad Gita)",
    "source": "The Bhagavad Gita, ch. 2, verse 47 (Stephen Mitchell translation, Harmony, 2000)",
    "lesson": "Own your effort fully and let go of the result.",
    "category": "detachment",
    "action": "Name one outcome you can't control and rewrite your goal as the action you can actually take.",
    "genre": "Eastern Wisdom",
    "sourceType": "Scripture"
  },
  {
    "id": "buddha-thoughts",
    "text": "All that we are is the result of what we have thought: it is founded on our thoughts, it is made up of our thoughts.",
    "author": "The Buddha",
    "source": "The Dhammapada, verse 1 (F. Max Müller translation, Sacred Books of the East, Vol. 10, 1881)",
    "lesson": "Your inner narrative builds the life you experience.",
    "category": "mind",
    "action": "Catch one recurring negative thought you tell yourself today and write the truer line to replace it.",
    "genre": "Eastern Wisdom",
    "sourceType": "Scripture"
  },
  {
    "id": "rumi-prison",
    "text": "Why do you stay in prison when the door is so wide open?",
    "author": "Rumi",
    "source": "The Essential Rumi, translated by Coleman Barks with John Moyne (HarperOne, 1995)",
    "lesson": "Most of your cages are unlocked; you just haven't walked out.",
    "category": "freedom",
    "action": "Name one self-imposed limit you treat as fixed and take one step today as if it weren't real.",
    "genre": "Eastern Wisdom",
    "sourceType": "Poem"
  },
  {
    "id": "thiruvalluvar-undismayed",
    "text": "Who strive with undismayed, unfaltering mind, at length shall leave opposing fate behind.",
    "author": "Thiruvalluvar",
    "source": "Tirukkural, couplet 620 (G.U. Pope translation, 1886)",
    "lesson": "A steady, unshaken mind eventually outlasts bad luck.",
    "category": "perseverance",
    "action": "Pick the setback you keep replaying and write the next concrete move you'll make despite it.",
    "genre": "Eastern Wisdom",
    "sourceType": "Poem"
  },
  {
    "id": "kabir-today",
    "text": "Tomorrow's work do today, and today's work now; if the moment is lost, the work how will you do?",
    "author": "Kabir",
    "source": "Kabir, doha \"Kal kare so aaj kar\" (traditional Hindi couplet)",
    "lesson": "Pull tomorrow's work into now before the moment slips.",
    "category": "urgency",
    "action": "Take one thing you scheduled for later this week and do its first step in the next ten minutes.",
    "genre": "Eastern Wisdom",
    "sourceType": "Poem"
  },
  {
    "id": "laotzu-difficult",
    "text": "Confront the difficult while it is still easy; accomplish the great task by a series of small acts.",
    "author": "Lao Tzu",
    "source": "Tao Te Ching, ch. 63 (Stephen Mitchell translation, Harper & Row, 1988)",
    "lesson": "Tackle problems while small; build big things from small acts.",
    "category": "momentum",
    "action": "Spot one issue that's still tiny and easy to fix, and handle it now before it grows.",
    "genre": "Eastern Wisdom",
    "sourceType": "Scripture"
  },
  {
    "id": "meadows-purpose",
    "text": "The least obvious part of the system, its function or purpose, is often the most crucial determinant of the system's behavior.",
    "author": "Donella Meadows",
    "source": "Thinking in Systems: A Primer (2008), Chapter 1",
    "lesson": "A system's real purpose, not its stated one, drives its behavior.",
    "category": "systems",
    "action": "Write down what your team's process actually optimizes for, not what the doc says it does.",
    "genre": "Systems & Science",
    "sourceType": "Book"
  },
  {
    "id": "meadows-models",
    "text": "Remember, always, that everything you know, and everything everyone knows, is only a model. Get your model out there where it can be viewed. Invite others to challenge your assumptions and add their own.",
    "author": "Donella Meadows",
    "source": "Dancing With Systems (2001 essay, Donella Meadows Project / Whole Earth Review); also in Thinking in Systems (2008)",
    "lesson": "Everything you know is a model; expose it so others can sharpen it.",
    "category": "humility",
    "action": "Write your current plan's core assumption in one line and ask a teammate to poke holes in it today.",
    "genre": "Systems & Science",
    "sourceType": "Essay"
  },
  {
    "id": "feynman-fool",
    "text": "The first principle is that you must not fool yourself - and you are the easiest person to fool.",
    "author": "Richard Feynman",
    "source": "\"Cargo Cult Science,\" Caltech commencement address, 1974 (published in Engineering & Science, June 1974)",
    "lesson": "Guard hardest against fooling yourself.",
    "category": "integrity",
    "action": "Take one belief about your product you'd hate to be wrong about and find one fact that tests it.",
    "genre": "Systems & Science",
    "sourceType": "Speech"
  },
  {
    "id": "feynman-nature",
    "text": "For a successful technology, reality must take precedence over public relations, for Nature cannot be fooled.",
    "author": "Richard Feynman",
    "source": "Rogers Commission Report, Appendix F (\"Personal Observations on the Reliability of the Shuttle\"), 1986",
    "lesson": "Reality always beats the story you tell about it.",
    "category": "reality",
    "action": "Find one metric you've been spinning in updates and write down the unvarnished number instead.",
    "genre": "Systems & Science",
    "sourceType": "Essay"
  },
  {
    "id": "simon-attention",
    "text": "A wealth of information creates a poverty of attention.",
    "author": "Herbert Simon",
    "source": "\"Designing Organizations for an Information-Rich World,\" in Computers, Communications, and the Public Interest (Johns Hopkins Press, 1971)",
    "lesson": "More information just means attention is your real bottleneck.",
    "category": "attention",
    "action": "Close every tab and notification, then work on one thing only for the next twenty-five minutes.",
    "genre": "Systems & Science",
    "sourceType": "Essay"
  },
  {
    "id": "simon-design",
    "text": "Everyone designs who devises courses of action aimed at changing existing situations into preferred ones.",
    "author": "Herbert Simon",
    "source": "The Sciences of the Artificial (MIT Press, 1969), Ch. 3 \"The Science of Design\"",
    "lesson": "Anyone changing a situation toward a better one is designing.",
    "category": "design",
    "action": "Pick one annoying part of your day and sketch the small change that would make it work better.",
    "genre": "Systems & Science",
    "sourceType": "Book"
  },
  {
    "id": "munger-incentives",
    "text": "Never, ever, think about something else when you should be thinking about the power of incentives.",
    "author": "Charlie Munger",
    "source": "\"The Psychology of Human Misjudgment,\" Harvard speech, 1995",
    "lesson": "When behavior puzzles you, look first at the incentives.",
    "category": "incentives",
    "action": "Name one person acting in a way you don't get, then write down what they're actually rewarded for.",
    "genre": "Strategy & Money",
    "sourceType": "Speech"
  },
  {
    "id": "deming-system",
    "text": "A bad system will beat a good person every time.",
    "author": "W. Edwards Deming",
    "source": "W. Edwards Deming, four-day seminar, February 1993 (W. Edwards Deming Institute)",
    "lesson": "Fix the system before you blame the person inside it.",
    "category": "systems",
    "action": "Take one repeated mistake on your team and write the broken process behind it, not the name.",
    "genre": "Systems & Science",
    "sourceType": "Speech"
  },
  {
    "id": "ackoff-whole",
    "text": "A system is more than the sum of its parts; it is an indivisible whole. It loses its essential properties when it is taken apart.",
    "author": "Russell Ackoff",
    "source": "\"Science in the Systems Age: Beyond IE, OR and MS,\" Operations Research, Vol. 21 (1973), p. 664",
    "lesson": "A system's value lives in how its parts connect, not the parts alone.",
    "category": "systems",
    "action": "Pick one feature you're judging in isolation and write down how it works with everything around it.",
    "genre": "Systems & Science",
    "sourceType": "Book"
  },
  {
    "id": "ackoff-rightthing",
    "text": "It is much better to do the right thing wrong than the wrong thing right.",
    "author": "Russell Ackoff",
    "source": "Russell Ackoff, recorded talk \"If Russ Ackoff had given a TED talk\" (c. 1994)",
    "lesson": "Doing the right thing badly beats polishing the wrong thing.",
    "category": "effectiveness",
    "action": "Check your top task and confirm it's the right problem before you spend another hour perfecting it.",
    "genre": "Systems & Science",
    "sourceType": "Speech"
  },
  {
    "id": "kahneman-wysiati",
    "text": "What you see is all there is.",
    "author": "Daniel Kahneman",
    "source": "Thinking, Fast and Slow (2011), Part 1 (the WYSIATI principle)",
    "lesson": "Your mind treats the visible evidence as the whole story.",
    "category": "bias",
    "action": "Before your next decision, write down one important thing you might not be seeing yet.",
    "genre": "Systems & Science",
    "sourceType": "Book"
  },
  {
    "id": "kahneman-premortem",
    "text": "Imagine that we are a year into the future. We implemented the plan as it now exists. The outcome was a disaster. Please take 5 to 10 minutes to write a brief history of that disaster.",
    "author": "Daniel Kahneman",
    "source": "Thinking, Fast and Slow (2011), p. 264 (premortem, crediting Gary Klein)",
    "lesson": "Imagining failure in advance surfaces risks optimism hides.",
    "category": "decision",
    "action": "Spend five minutes writing the story of how your current plan failed a year from now, then fix one cause.",
    "genre": "Systems & Science",
    "sourceType": "Book"
  },
  {
    "id": "taleb-wind",
    "text": "Wind extinguishes a candle and energizes fire. Likewise with randomness, uncertainty, chaos: you want to use them, not hide from them.",
    "author": "Nassim Taleb",
    "source": "Antifragile: Things That Gain from Disorder (2012), Prologue (\"How to Love the Wind\")",
    "lesson": "Build so that disorder strengthens you instead of breaking you.",
    "category": "antifragility",
    "action": "Name one source of chaos in your work and write down how you could turn it into an advantage.",
    "genre": "Systems & Science",
    "sourceType": "Book"
  },
  {
    "id": "taleb-vianegativa",
    "text": "We know what is wrong with more certainty than we know anything else.",
    "author": "Nassim Taleb",
    "source": "Antifragile: Things That Gain from Disorder (2012), on via negativa / subtractive knowledge",
    "lesson": "Removing what's clearly wrong is surer than adding what might be right.",
    "category": "via-negativa",
    "action": "Find one obviously broken thing in your product or routine and remove it today.",
    "genre": "Systems & Science",
    "sourceType": "Book"
  },
  {
    "id": "boyd-people",
    "text": "People, ideas, machines - in that order.",
    "author": "John Boyd",
    "source": "Quoted in Robert Coram, Boyd: The Fighter Pilot Who Changed the Art of War (2002); from Boyd's briefings",
    "lesson": "People come before ideas, and ideas before machines.",
    "category": "priorities",
    "action": "Before buying another tool, write down whether the right person or idea would fix the problem instead.",
    "genre": "Systems & Science",
    "sourceType": "Book"
  },
  {
    "id": "wilson-paleolithic",
    "text": "We have Paleolithic emotions, medieval institutions, and god-like technology.",
    "author": "E.O. Wilson",
    "source": "E.O. Wilson, debate at the Harvard Museum of Natural History, 9 September 2009",
    "lesson": "Our instincts and institutions lag far behind our tools.",
    "category": "technology",
    "action": "Name one powerful tool you use and write down one guardrail your old habits still need around it.",
    "genre": "Systems & Science",
    "sourceType": "Speech"
  },
  {
    "id": "lamott-firstdraft",
    "text": "Almost all good writing begins with terrible first efforts. You need to start somewhere.",
    "author": "Anne Lamott",
    "source": "Bird by Bird: Some Instructions on Writing and Life (1994), chapter \"Shitty First Drafts\"",
    "lesson": "Every good thing starts as a rough, ugly first attempt.",
    "category": "writing",
    "action": "Open the doc you've been avoiding and write the worst possible first draft for ten minutes straight.",
    "genre": "Craft & Creativity",
    "sourceType": "Book"
  },
  {
    "id": "pressfield-resistance",
    "text": "Resistance is experienced as fear; the degree of fear equates to the strength of Resistance. Therefore the more fear we feel about a specific enterprise, the more certain we can be that that enterprise is important to us.",
    "author": "Steven Pressfield",
    "source": "The War of Art: Break Through the Blocks and Win Your Inner Creative Battles (2002)",
    "lesson": "The work you fear most is usually the work that matters most.",
    "category": "resistance",
    "action": "Name the task you feel the most dread about and start it before anything easier today.",
    "genre": "Craft & Creativity",
    "sourceType": "Book"
  },
  {
    "id": "pressfield-pro",
    "text": "The amateur tweets. The pro works.",
    "author": "Steven Pressfield",
    "source": "Turning Pro: Tap Your Inner Power and Create Your Life's Work (2012)",
    "lesson": "Talking about the work is not the work.",
    "category": "discipline",
    "action": "Close the app you broadcast on and spend the next thirty minutes only making the actual thing.",
    "genre": "Craft & Creativity",
    "sourceType": "Book"
  },
  {
    "id": "godin-ship",
    "text": "The only purpose of starting is to finish, and while the projects we do are never really finished, they must ship.",
    "author": "Seth Godin",
    "source": "Linchpin: Are You Indispensable? (2010)",
    "lesson": "Starting only counts if it ends in something released.",
    "category": "shipping",
    "action": "Pick one open project and set a hard ship date for it on your calendar before you close this.",
    "genre": "Craft & Creativity",
    "sourceType": "Book"
  },
  {
    "id": "angelou-creativity",
    "text": "You can't use up creativity. The more you use, the more you have.",
    "author": "Maya Angelou",
    "source": "Maya Angelou interview, Bell Telephone Magazine (1982); reprinted in Conversations with Maya Angelou, ed. Jeffrey M. Elliot (1989)",
    "lesson": "Creativity grows from use, not from rationing.",
    "category": "creativity",
    "action": "Make one small creative thing today without saving the idea for a more important moment.",
    "genre": "Craft & Creativity",
    "sourceType": "Interview"
  },
  {
    "id": "baldwin-process",
    "text": "The artist cannot and must not take anything for granted, but must drive to the heart of every answer and expose the question the answer hides.",
    "author": "James Baldwin",
    "source": "\"The Creative Process,\" essay in Creative America (Ridge Press, 1962)",
    "lesson": "Don't accept the easy answer; dig out the question it's hiding.",
    "category": "craft",
    "action": "Take an answer you accepted at work and write down the harder question it was quietly avoiding.",
    "genre": "Craft & Creativity",
    "sourceType": "Essay"
  },
  {
    "id": "morrison-writeit",
    "text": "If you find a book you really want to read but it hasn't been written yet, then you must write it.",
    "author": "Toni Morrison",
    "source": "Address to the Ohio Arts Council (1981), reported in The Cincinnati Enquirer (27 Sept 1981) via Gannett News Service",
    "lesson": "If the thing you want doesn't exist, you're the one to build it.",
    "category": "agency",
    "action": "Name one product or resource you keep wishing existed and sketch its first piece today.",
    "genre": "Craft & Creativity",
    "sourceType": "Speech"
  },
  {
    "id": "morrison-free",
    "text": "When you get these jobs that you have been so brilliantly trained for, just remember that your real job is that if you are free, you need to free somebody else. If you have some power, then your job is to empower somebody else.",
    "author": "Toni Morrison",
    "source": "O, The Oprah Magazine interview (November 2003)",
    "lesson": "Power and freedom are only worth having if you pass them on.",
    "category": "leadership",
    "action": "Use one bit of your access or skill to open a door for someone else this week, starting now.",
    "genre": "Craft & Creativity",
    "sourceType": "Interview"
  },
  {
    "id": "frankl-success",
    "text": "Don't aim at success. The more you aim at it and make it a target, the more you are going to miss it. For success, like happiness, cannot be pursued; it must ensue.",
    "author": "Viktor Frankl",
    "source": "Man's Search for Meaning, preface to the 1992 edition (English translation; original 1946)",
    "lesson": "Success follows good work; chasing it directly drives it away.",
    "category": "meaning",
    "action": "Drop one metric you're obsessing over and refocus today's effort on doing the work well instead.",
    "genre": "Mind & Character",
    "sourceType": "Book"
  },
  {
    "id": "jung-heart",
    "text": "Your vision will become clear only when you can look into your own heart. Who looks outside, dreams; who looks inside, awakes.",
    "author": "Carl Jung",
    "source": "Letter to Fanny Bowditch, 22 October 1916, in C.G. Jung Letters, Vol. 1: 1906-1950 (Princeton/Bollingen), p. 33",
    "lesson": "Clarity comes from looking inward, not scanning outside for cues.",
    "category": "psychology",
    "action": "Write down what you actually want from your current project, not what looks good to others.",
    "genre": "Mind & Character",
    "sourceType": "Letter"
  },
  {
    "id": "leguin-freedom",
    "text": "We will need writers who can remember freedom. Poets, visionaries, the realists of a larger reality.",
    "author": "Ursula K. Le Guin",
    "source": "National Book Awards acceptance speech, Medal for Distinguished Contribution to American Letters (19 November 2014)",
    "lesson": "The future needs people who can still picture something better.",
    "category": "vision",
    "action": "Write one sentence describing the larger reality your work is trying to build toward.",
    "genre": "Craft & Creativity",
    "sourceType": "Speech"
  },
  {
    "id": "ogilvy-consumer",
    "text": "The consumer isn't a moron; she is your wife. You insult her intelligence if you assume that a mere slogan and a few vapid adjectives will persuade her to buy anything.",
    "author": "David Ogilvy",
    "source": "Confessions of an Advertising Man (1963), p. 96",
    "lesson": "Respect your customer's intelligence instead of dressing up empty claims.",
    "category": "craft",
    "action": "Find one vague line in your marketing and rewrite it as a concrete, honest reason to care.",
    "genre": "Craft & Creativity",
    "sourceType": "Book"
  },
  {
    "id": "rand-good",
    "text": "Don't try to be original. Just try to be good.",
    "author": "Paul Rand",
    "source": "Interview with Steven Heller (conducted 1990), published in Design Dialogues (Allworth Press, 1998)",
    "lesson": "Chase quality, not novelty; original follows from good.",
    "category": "craft",
    "action": "Stop hunting for a clever angle and make the next thing simply work well instead.",
    "genre": "Craft & Creativity",
    "sourceType": "Interview"
  },
  {
    "id": "pressfield-agents",
    "text": "We were put here on earth to act as agents of the Infinite, to bring into existence that which is not yet, but which will be, through us.",
    "author": "Steven Pressfield",
    "source": "The War of Art: Break Through the Blocks and Win Your Inner Creative Battles (2002)",
    "lesson": "Your job is to bring into being what doesn't yet exist.",
    "category": "purpose",
    "action": "Name the one thing only you can build right now and do one real piece of it today.",
    "genre": "Craft & Creativity",
    "sourceType": "Book"
  },
  {
    "id": "anand-badi",
    "text": "Babumoshai, zindagi badi honi chahiye... lambi nahi.",
    "author": "Anand Sehgal (Rajesh Khanna)",
    "source": "Anand (1971)",
    "lesson": "A life's worth is measured by its depth and impact, not the number of years it lasts.",
    "category": "Meaning",
    "action": "Name one thing you'd do today if you knew it would matter more than another decade of routine, then do the first step now.",
    "genre": "Cinema",
    "sourceType": "Movie"
  },
  {
    "id": "anand-kathputli",
    "text": "Babumoshai, zindagi aur maut uparwale ke haath hai. Usse na toh aap badal sakte hain na main. Hum sab toh rangmanch ki kathputliyan hain jinki dor uparwale ki ungliyon mein bandhi hai.",
    "author": "Anand Sehgal (Rajesh Khanna)",
    "source": "Anand (1971)",
    "lesson": "Peace comes from releasing your grip on what you were never in control of.",
    "category": "Acceptance",
    "action": "Write down one thing you've been straining to control that isn't yours to control, then cross it off and redirect that energy.",
    "genre": "Cinema",
    "sourceType": "Movie"
  },
  {
    "id": "deewaar-maa",
    "text": "Mere paas maa hai.",
    "author": "Ravi Verma (Shashi Kapoor)",
    "source": "Deewaar (1975)",
    "lesson": "What truly makes you rich is rarely the thing you can put a price on.",
    "category": "Values",
    "action": "Text one person who is your real wealth and tell them specifically why they matter to you, in two sentences.",
    "genre": "Cinema",
    "sourceType": "Movie"
  },
  {
    "id": "deewaar-pheke",
    "text": "Main aaj bhi pheke hue paise nahi uthata.",
    "author": "Vijay Verma (Amitabh Bachchan)",
    "source": "Deewaar (1975)",
    "lesson": "Your dignity sets a floor that no amount of money or pressure should be allowed to drop below.",
    "category": "Self-respect",
    "action": "Identify one deal or favor that quietly costs your self-respect, and decline it today in one clear line.",
    "genre": "Cinema",
    "sourceType": "Movie"
  },
  {
    "id": "sholay-dar",
    "text": "Jo dar gaya, samjho mar gaya.",
    "author": "Gabbar Singh (Amjad Khan)",
    "source": "Sholay (1975)",
    "lesson": "Fear, when it freezes you, ends things faster than the danger you were afraid of.",
    "category": "Courage",
    "action": "Pick the one task you've been avoiding out of fear and take the smallest possible action on it in the next 60 seconds.",
    "genre": "Cinema",
    "sourceType": "Movie"
  },
  {
    "id": "sholay-kitne",
    "text": "Kitne aadmi the?",
    "author": "Gabbar Singh (Amjad Khan)",
    "source": "Sholay (1975)",
    "lesson": "Honest accounting of what actually happened beats any excuse for why it went wrong.",
    "category": "Accountability",
    "action": "Take one thing that slipped this week and write the plain factual reason it failed, with no justification attached.",
    "genre": "Cinema",
    "sourceType": "Movie"
  },
  {
    "id": "zanjeer-sharafat",
    "text": "Jab tak baithne ko na kaha jaaye, sharafat se khade raho. Yeh police station hai, tumhare baap ka ghar nahi.",
    "author": "Inspector Vijay Khanna (Amitabh Bachchan)",
    "source": "Zanjeer (1973)",
    "lesson": "Standing firm on principle commands more respect than bending to whoever is loudest in the room.",
    "category": "Integrity",
    "action": "Find one place today where you've been deferring to status over what's right, and hold your line politely but firmly.",
    "genre": "Cinema",
    "sourceType": "Movie"
  },
  {
    "id": "mughal-pyar",
    "text": "Pyar kiya to darna kya.",
    "author": "Anarkali (Madhubala)",
    "source": "Mughal-e-Azam (1960)",
    "lesson": "If a choice is truly yours and truly right, owning it openly costs less than hiding it.",
    "category": "Courage",
    "action": "Say one true thing out loud today that you've been keeping quiet about out of fear of judgment.",
    "genre": "Cinema",
    "sourceType": "Movie"
  },
  {
    "id": "mrindia-mogambo",
    "text": "Mogambo khush hua.",
    "author": "Mogambo (Amrish Puri)",
    "source": "Mr. India (1987)",
    "lesson": "Naming what genuinely pleases you helps you notice and repeat what's working.",
    "category": "Recognition",
    "action": "End your day by naming one specific thing you did well, out loud, before you list anything that went wrong.",
    "genre": "Cinema",
    "sourceType": "Movie"
  },
  {
    "id": "kaalia-line",
    "text": "Hum jahan khade ho jaate hain, line wahin se shuru hoti hai.",
    "author": "Raju (Amitabh Bachchan)",
    "source": "Kaalia (1981)",
    "lesson": "Confidence is partly a decision to treat your own position as the starting point, not the back of the queue.",
    "category": "Self-belief",
    "action": "In your next meeting or message, lead with your view first instead of waiting to see where everyone else lands.",
    "genre": "Cinema",
    "sourceType": "Movie"
  },
  {
    "id": "3idiots-aal",
    "text": "Aal izz well",
    "author": "Ranchhoddas 'Rancho' Chanchad (Aamir Khan)",
    "source": "3 Idiots (2009)",
    "lesson": "A calming cue doesn't fix the problem, but it steadies you enough to actually face it.",
    "category": "Calm",
    "action": "Before your next stressful task, take three slow breaths and tell yourself it's handled, then start the very first step.",
    "genre": "Cinema",
    "sourceType": "Movie"
  },
  {
    "id": "3idiots-kaabil",
    "text": "Bachcha, kaabil bano, kaabil. Kaamyaabi toh saali jhak maarke peeche bhagegi.",
    "author": "Rancho, via Farhan (R. Madhavan) in 3 Idiots",
    "source": "3 Idiots (2009)",
    "lesson": "Chase competence relentlessly and the rewards tend to follow on their own.",
    "category": "Mastery",
    "action": "Spend 15 minutes today deliberately practicing the one skill your goal actually depends on, not the busywork around it.",
    "genre": "Cinema",
    "sourceType": "Movie"
  },
  {
    "id": "chakde-sattar",
    "text": "Sattar minute hai tumhare paas, shaayad tumhari zindagi ke sabse khaas sattar minute. Aaj tum achha khelo ya bura, yeh sattar minute tumhe zindagi bhar yaad rahenge.",
    "author": "Kabir Khan (Shah Rukh Khan)",
    "source": "Chak De! India (2007)",
    "lesson": "Treating a short, defined window as sacred concentrates your whole effort where it counts.",
    "category": "Focus",
    "action": "Block 70 minutes for your single most important task today, kill all notifications, and give it everything you have.",
    "genre": "Cinema",
    "sourceType": "Movie"
  },
  {
    "id": "rdb-zimmedaari",
    "text": "Zindagi jeene ke do hi tarike hote hain. Ek, jo ho raha hai hone do, bardaasht karte jao. Ya phir, zimmedaari uthao use badalne ki.",
    "author": "Daljeet 'DJ' Singh (Aamir Khan)",
    "source": "Rang De Basanti (2006)",
    "lesson": "You either tolerate what's wrong or you take ownership of changing it, and only one of those moves you forward.",
    "category": "Agency",
    "action": "Pick one thing you've been merely enduring and take a single concrete step today to change it instead.",
    "genre": "Cinema",
    "sourceType": "Movie"
  },
  {
    "id": "rdb-behtar",
    "text": "Koi bhi desh perfect nahi hota, use behtar banana padta hai.",
    "author": "Flight Lt. Ajay Singh Rathod (R. Madhavan)",
    "source": "Rang De Basanti (2006)",
    "lesson": "Nothing worth belonging to is flawless, so the real work is improving it rather than abandoning it.",
    "category": "Responsibility",
    "action": "Choose one community or project you complain about and contribute one small fix to it today instead of just criticizing.",
    "genre": "Cinema",
    "sourceType": "Movie"
  },
  {
    "id": "swades-kaabiliyat",
    "text": "Main nahi maanta hamara desh duniya ka sabse mahaan desh hai. Lekin yeh zaroor maanta hoon ki hum mein kaabiliyat hai, taaqat hai, apne desh ko mahaan banane ki.",
    "author": "Mohan Bhargav (Shah Rukh Khan)",
    "source": "Swades (2004)",
    "lesson": "Clear-eyed honesty about where you fall short, paired with belief in your capacity, beats hollow pride.",
    "category": "Honesty",
    "action": "Name one weakness honestly and one real strength you'll use to close it, then act on the strength today.",
    "genre": "Cinema",
    "sourceType": "Movie"
  },
  {
    "id": "znmd-seize",
    "text": "Seize the day, my friend. Pehle is din ko poori tarah jiyo, phir chaalis ke baare mein sochna.",
    "author": "Laila (Katrina Kaif)",
    "source": "Zindagi Na Milegi Dobara (2011)",
    "lesson": "Living this day fully matters more than worrying about a future that may never arrive.",
    "category": "Presence",
    "action": "Do one thing today purely because it makes today better, not because it serves some distant plan.",
    "genre": "Cinema",
    "sourceType": "Movie"
  },
  {
    "id": "znmd-zinda",
    "text": "Dilon mein tum apni betaabiyan leke chal rahe ho, toh zinda ho tum.",
    "author": "Imran Qureshi (Farhan Akhtar)",
    "source": "Zindagi Na Milegi Dobara (2011)",
    "lesson": "Restlessness and longing are signs you're still fully alive, not problems to suppress.",
    "category": "Aliveness",
    "action": "Write down one restless desire you've been dismissing as impractical, and take one tiny step toward it today.",
    "genre": "Cinema",
    "sourceType": "Movie"
  },
  {
    "id": "gullyboy-time",
    "text": "Apna time aayega.",
    "author": "Murad (Ranveer Singh)",
    "source": "Gully Boy (2019)",
    "lesson": "Belief that your moment is coming keeps you working through the stretch when nothing seems to land yet.",
    "category": "Hope",
    "action": "On your long-term goal, do the next unglamorous rep today and trust the timeline instead of demanding instant proof.",
    "genre": "Cinema",
    "sourceType": "Movie"
  },
  {
    "id": "dangal-chhoriyan",
    "text": "Mhaari chhoriyaan chhoron se kam hai ke?",
    "author": "Mahavir Singh Phogat (Aamir Khan)",
    "source": "Dangal (2016)",
    "lesson": "Capability has nothing to do with the category someone tried to sort you into.",
    "category": "Equality",
    "action": "Catch one assumption today about what you or someone else can't do because of a label, and challenge it with an action.",
    "genre": "Cinema",
    "sourceType": "Movie"
  },
  {
    "id": "lagaan-sapne",
    "text": "Chhoti chhoti aankhein, aur bade bade sapne. Aur sapne wohi saakaar kar sakte hain, jo unhe dekhte hain.",
    "author": "Bhuvan (Aamir Khan)",
    "source": "Lagaan: Once Upon a Time in India (2001)",
    "lesson": "Only the people willing to dream big in the first place ever get to make those dreams real.",
    "category": "Vision",
    "action": "Write down one dream you've shrunk to feel realistic, restore it to full size, and note the first move toward it.",
    "genre": "Cinema",
    "sourceType": "Movie"
  },
  {
    "id": "dch-ret",
    "text": "Is ret ko jitna apne haath mein bandh karne ki koshish karoge, utni hi tezi se yeh phisal jaayegi.",
    "author": "Siddharth 'Sid' Sinha (Akshaye Khanna)",
    "source": "Dil Chahta Hai (2001)",
    "lesson": "The harder you clutch at a person or outcome, the faster you tend to lose it.",
    "category": "Acceptance",
    "action": "Identify one thing you've been gripping too tightly and consciously loosen your hold on it for the rest of today.",
    "genre": "Cinema",
    "sourceType": "Movie"
  },
  {
    "id": "deadpoets-carpe",
    "text": "Carpe diem. Seize the day, boys. Make your lives extraordinary.",
    "author": "John Keating (Robin Williams)",
    "source": "Dead Poets Society (1989)",
    "lesson": "An ordinary life is a default you have to actively refuse, one day at a time.",
    "category": "Seize",
    "action": "Do one thing today that your future self would call extraordinary, however small, instead of coasting on autopilot.",
    "genre": "Cinema",
    "sourceType": "Movie"
  },
  {
    "id": "yoda-try",
    "text": "Do. Or do not. There is no try.",
    "author": "Master Yoda",
    "source": "Star Wars: Episode V - The Empire Strikes Back (1980)",
    "lesson": "Half-committing while calling it trying is just a softer way of not doing the thing.",
    "category": "Commitment",
    "action": "Take one goal you've been trying to do and commit to a specific action with a time today, then actually do it.",
    "genre": "Cinema",
    "sourceType": "Movie"
  },
  {
    "id": "coolhand-communicate",
    "text": "What we've got here is failure to communicate.",
    "author": "The Captain (Strother Martin)",
    "source": "Cool Hand Luke (1967)",
    "lesson": "Most conflicts are not disagreements but messages that never got clearly sent or received.",
    "category": "Communication",
    "action": "Pick one tense situation and send one plain message stating what you actually mean, with no hinting.",
    "genre": "Cinema",
    "sourceType": "Movie"
  },
  {
    "id": "forrest-chocolates",
    "text": "My mama always said life was like a box of chocolates. You never know what you're gonna get.",
    "author": "Forrest Gump (Tom Hanks)",
    "source": "Forrest Gump (1994)",
    "lesson": "You can't predict what each day hands you, so staying open beats demanding certainty.",
    "category": "Uncertainty",
    "action": "Say yes to one small unplanned thing today instead of insisting on knowing exactly how it'll go.",
    "genre": "Cinema",
    "sourceType": "Movie"
  },
  {
    "id": "vader-father",
    "text": "No. I am your father.",
    "author": "Darth Vader (David Prowse / voice James Earl Jones)",
    "source": "Star Wars: Episode V - The Empire Strikes Back (1980)",
    "lesson": "Some truths land hard, but facing them is the only way past the story you'd rather believe.",
    "category": "Truth",
    "action": "Name one uncomfortable truth about your situation you've been dodging, and write it down in one honest sentence.",
    "genre": "Cinema",
    "sourceType": "Movie"
  },
  {
    "id": "lotr-time",
    "text": "All we have to decide is what to do with the time that is given us.",
    "author": "Gandalf (Ian McKellen)",
    "source": "The Lord of the Rings: The Fellowship of the Ring (2001)",
    "lesson": "You don't get to choose your circumstances, only what you do with the time inside them.",
    "category": "Time",
    "action": "Stop wishing your situation were different for one minute and decide one useful thing to do with today's hours.",
    "genre": "Cinema",
    "sourceType": "Movie"
  },
  {
    "id": "batman-fall",
    "text": "Why do we fall, sir? So that we can learn to pick ourselves up.",
    "author": "Alfred Pennyworth (Michael Caine)",
    "source": "Batman Begins (2005)",
    "lesson": "The point of a setback is the practice it gives you at getting back up.",
    "category": "Resilience",
    "action": "Take one recent failure and write the single lesson it taught you, then apply that lesson to one action today.",
    "genre": "Cinema",
    "sourceType": "Movie"
  },
  {
    "id": "help-worth",
    "text": "You is kind. You is smart. You is important.",
    "author": "Aibileen Clark (Viola Davis)",
    "source": "The Help (2011)",
    "lesson": "Worth that you repeat to yourself often enough starts to become something you actually believe.",
    "category": "Worth",
    "action": "Tell yourself or someone who needs it three plain affirmations of worth today, and mean each one.",
    "genre": "Cinema",
    "sourceType": "Movie"
  },
  {
    "id": "shawshank-living",
    "text": "Get busy living, or get busy dying.",
    "author": "Andy Dufresne / Red (Tim Robbins / Morgan Freeman)",
    "source": "The Shawshank Redemption (1994)",
    "lesson": "Drifting without purpose is its own slow kind of giving up, so choose to actively live.",
    "category": "Hope",
    "action": "Pick one thing that makes you feel alive and schedule it into today, not someday.",
    "genre": "Cinema",
    "sourceType": "Movie"
  },
  {
    "id": "shawshank-hope",
    "text": "Remember, Red, hope is a good thing, maybe the best of things, and no good thing ever dies.",
    "author": "Andy Dufresne (Tim Robbins)",
    "source": "The Shawshank Redemption (1994)",
    "lesson": "Hope kept alive is what carries you through the stretches where nothing else does.",
    "category": "Hope",
    "action": "Write down one thing you're genuinely hopeful about and keep it somewhere you'll see it when today gets heavy.",
    "genre": "Cinema",
    "sourceType": "Movie"
  },
  {
    "id": "fewgoodmen-truth",
    "text": "You can't handle the truth!",
    "author": "Col. Nathan Jessup (Jack Nicholson)",
    "source": "A Few Good Men (1992)",
    "lesson": "Assuming others can't handle the truth is often an excuse for avoiding the discomfort of telling it.",
    "category": "Truth",
    "action": "Give one person the honest feedback you've been withholding because you assumed they couldn't take it.",
    "genre": "Cinema",
    "sourceType": "Movie"
  },
  {
    "id": "gwtw-damn",
    "text": "Frankly, my dear, I don't give a damn.",
    "author": "Rhett Butler (Clark Gable)",
    "source": "Gone with the Wind (1939)",
    "lesson": "There's freedom in finally refusing to keep pouring yourself into what no longer deserves it.",
    "category": "Boundaries",
    "action": "Identify one thing draining you that doesn't deserve your energy, and consciously stop giving it any today.",
    "genre": "Cinema",
    "sourceType": "Movie"
  },
  {
    "id": "mockingbird-empathy",
    "text": "You never really understand a person until you consider things from his point of view. Until you climb into his skin and walk around in it.",
    "author": "Atticus Finch (Gregory Peck)",
    "source": "To Kill a Mockingbird (1962)",
    "lesson": "You can't fairly judge anyone until you've genuinely tried to see the situation through their eyes.",
    "category": "Empathy",
    "action": "Pick someone who frustrated you recently and write two real reasons they might have acted that way.",
    "genre": "Cinema",
    "sourceType": "Movie"
  },
  {
    "id": "pursuit-dream",
    "text": "Don't ever let somebody tell you you can't do something. Not even me. All right? You got a dream, you gotta protect it. People can't do something themselves, they wanna tell you you can't do it. If you want something, go get it. Period.",
    "author": "Chris Gardner (Will Smith)",
    "source": "The Pursuit of Happyness (2006)",
    "lesson": "Other people's limits are theirs, not yours, so guard your goal from anyone who needs you to fail.",
    "category": "Perseverance",
    "action": "Note one doubt someone planted in you, decide whether it's actually true, and take one step toward your goal regardless.",
    "genre": "Cinema",
    "sourceType": "Movie"
  },
  {
    "id": "whiplash-goodjob",
    "text": "There are no two words in the English language more harmful than 'good job.'",
    "author": "Terence Fletcher (J.K. Simmons)",
    "source": "Whiplash (2014)",
    "lesson": "Settling for good enough can quietly cap how far you ever push yourself.",
    "category": "Growth",
    "action": "Take something you'd call 'good enough' today and spend 15 minutes making it genuinely better.",
    "genre": "Cinema",
    "sourceType": "Movie"
  },
  {
    "id": "darkknight-villain",
    "text": "You either die a hero, or you live long enough to see yourself become the villain.",
    "author": "Harvey Dent (Aaron Eckhart)",
    "source": "The Dark Knight (2008)",
    "lesson": "Staying good over time takes active vigilance, because slow drift is how good people become the thing they fought.",
    "category": "Integrity",
    "action": "Check one habit or compromise you've been excusing lately and ask honestly if it's drifting from who you want to be.",
    "genre": "Cinema",
    "sourceType": "Movie"
  },
  {
    "id": "oogway-present",
    "text": "Yesterday is history, tomorrow is a mystery, but today is a gift. That is why it is called the present.",
    "author": "Master Oogway",
    "source": "Kung Fu Panda (2008)",
    "lesson": "Today is the only stretch of time you can actually act in, which makes it the one that counts.",
    "category": "Presence",
    "action": "Put your phone down for ten minutes and give your full attention to whatever is in front of you right now.",
    "genre": "Cinema",
    "sourceType": "Movie"
  },
  {
    "id": "ratatouille-anywhere",
    "text": "Not everyone can become a great artist, but a great artist can come from anywhere.",
    "author": "Anton Ego (Peter O'Toole)",
    "source": "Ratatouille (2007)",
    "lesson": "Talent isn't confined to the people from the expected places or backgrounds.",
    "category": "Potential",
    "action": "Pursue one thing you've assumed wasn't for people like you, and take the first concrete step toward it today.",
    "genre": "Cinema",
    "sourceType": "Movie"
  },
  {
    "id": "matrix-door",
    "text": "I'm trying to free your mind, Neo. But I can only show you the door. You're the one that has to walk through it.",
    "author": "Morpheus (Laurence Fishburne)",
    "source": "The Matrix (1999)",
    "lesson": "Others can point the way, but the actual crossing is something only you can do.",
    "category": "Agency",
    "action": "Stop waiting for more advice on one decision and make the call yourself today, then act on it.",
    "genre": "Cinema",
    "sourceType": "Movie"
  },
  {
    "id": "interstellar-rage",
    "text": "Do not go gentle into that good night. Old age should burn and rave at close of day. Rage, rage against the dying of the light.",
    "author": "Professor Brand (Michael Caine), quoting Dylan Thomas",
    "source": "Interstellar (2014)",
    "lesson": "Some things are worth fighting for fiercely rather than accepting quietly.",
    "category": "Defiance",
    "action": "Pick one thing you've been passively letting slip away and push back on it with one bold action today.",
    "genre": "Cinema",
    "sourceType": "Movie"
  },
  {
    "id": "gladiator-echoes",
    "text": "Brothers, what we do in life echoes in eternity.",
    "author": "Maximus (Russell Crowe)",
    "source": "Gladiator (2000)",
    "lesson": "Today's actions ripple far beyond the moment, so choose them as if they'll outlast you.",
    "category": "Legacy",
    "action": "Do one thing today you'd be proud to have remembered, and skip one you'd rather forget.",
    "genre": "Cinema",
    "sourceType": "Movie"
  }
]
